README.rst
pyproject.toml
setup.py
tutor_license.egg-info/PKG-INFO
tutor_license.egg-info/SOURCES.txt
tutor_license.egg-info/dependency_links.txt
tutor_license.egg-info/entry_points.txt
tutor_license.egg-info/requires.txt
tutor_license.egg-info/top_level.txt
tutorlicense/__about__.py
tutorlicense/__init__.py
tutorlicense/cmd.c
tutorlicense/plugin.py