Metadata-Version: 2.1
Name: tutor-license
Version: 16.0.0
Summary: Tutor license management plugin
Home-page: https://overhang.io/tutor/
Author: Overhang.IO
Author-email: regis@overhang.io
Project-URL: Homepage, https://overhang.io/tutor/
Classifier: Development Status :: 5 - Production/Stable
Classifier: Intended Audience :: Developers
Classifier: License :: Other/Proprietary License
Classifier: Operating System :: OS Independent
Classifier: Programming Language :: Python
Classifier: Programming Language :: Python :: 3.8
Classifier: Programming Language :: Python :: 3.9
Classifier: Programming Language :: Python :: 3.10
Classifier: Programming Language :: Python :: 3.11
Requires-Python: >=3.8
